rapidocr_onnxruntime/__init__.py
rapidocr_onnxruntime/config.yaml
rapidocr_onnxruntime/main.py
rapidocr_onnxruntime/cal_rec_boxes/__init__.py
rapidocr_onnxruntime/cal_rec_boxes/main.py
rapidocr_onnxruntime/ch_ppocr_cls/__init__.py
rapidocr_onnxruntime/ch_ppocr_cls/text_cls.py
rapidocr_onnxruntime/ch_ppocr_cls/utils.py
rapidocr_onnxruntime/ch_ppocr_det/__init__.py
rapidocr_onnxruntime/ch_ppocr_det/text_detect.py
rapidocr_onnxruntime/ch_ppocr_det/utils.py
rapidocr_onnxruntime/ch_ppocr_rec/__init__.py
rapidocr_onnxruntime/ch_ppocr_rec/text_recognize.py
rapidocr_onnxruntime/ch_ppocr_rec/utils.py
rapidocr_onnxruntime/models/ch_PP-OCRv4_det_infer.onnx
rapidocr_onnxruntime/models/ch_PP-OCRv4_rec_infer.onnx
rapidocr_onnxruntime/models/ch_ppocr_mobile_v2.0_cls_infer.onnx
rapidocr_onnxruntime/utils/__init__.py
rapidocr_onnxruntime/utils/infer_engine.py
rapidocr_onnxruntime/utils/load_image.py
rapidocr_onnxruntime/utils/logger.py
rapidocr_onnxruntime/utils/parse_parameters.py
rapidocr_onnxruntime/utils/process_img.py
rapidocr_onnxruntime/utils/vis_res.py
rapidocr_onnxruntime-1.4.3.dist-info/METADATA
rapidocr_onnxruntime-1.4.3.dist-info/WHEEL
rapidocr_onnxruntime-1.4.3.dist-info/entry_points.txt
rapidocr_onnxruntime-1.4.3.dist-info/top_level.txt
rapidocr_onnxruntime-1.4.3.dist-info/RECORD
